mhjson/__init__.py
mhjson/matcher.py
mhjson/query.py
mhjson-0.0.1.dist-info/METADATA
mhjson-0.0.1.dist-info/WHEEL
mhjson-0.0.1.dist-info/top_level.txt
mhjson-0.0.1.dist-info/RECORD
