Metadata-Version: 2.1
Name: mhjson
Version: 0.0.1
Summary: Query over Json file
Home-page: https://github.com/CodWize/mhjson
Author: Serega
Author-email: codwiz@yandex.ru
License: MIT
Keywords: Python,plugin
Classifier: Development Status :: 4 - Beta
Classifier: Intended Audience :: Developers
Classifier: Operating System :: OS Independent
Classifier: Topic :: Software Development :: Libraries :: Python Modules
Classifier: Programming Language :: Python :: 3
